pymbtiles/__init__.py
pymbtiles/mbtiles_tile_schema.sql
pymbtiles/ops.py
pymbtiles-0.5.0.dist-info/LICENSE.md
pymbtiles-0.5.0.dist-info/METADATA
pymbtiles-0.5.0.dist-info/WHEEL
pymbtiles-0.5.0.dist-info/top_level.txt
pymbtiles-0.5.0.dist-info/RECORD
