Metadata-Version: 2.1
Name: pymbtiles
Version: 0.5.0
Summary: MapBox Mbtiles Utilities
Home-page: https://github.com/consbio/pymbtiles
Author: Brendan C. Ward
Author-email: bcward@astutespruce.com
License: ISC
Platform: UNKNOWN
Provides-Extra: test
